funclibs/__init__.py
funclibs/elementary/Const.py
funclibs/elementary/__init__.py
funclibs/elementary/identity.py
funclibs/operator/Pointwise.py
funclibs/operator/Separable.py
funclibs/operator/Treelike.py
funclibs/operator/__init__.py
funclibs/tests/__init__.py
funclibs/tests/test_const.py
funclibs/tests/test_const_generic.py
funclibs/tests/test_identity.py
funclibs/tests/test_pointwise.py
funclibs/tests/test_separable.py
funclibs-0.7.5.dist-info/licenses/LICENSE.txt
funclibs-0.7.5.dist-info/METADATA
funclibs-0.7.5.dist-info/WHEEL
funclibs-0.7.5.dist-info/top_level.txt
funclibs-0.7.5.dist-info/RECORD
