Metadata-Version: 2.4
Name: funclibs
Version: 0.7.5
Summary: This project provides libraries concerning function.
Author-email: Johannes <johannes.programming@gmail.com>
License: The MIT License (MIT)
Project-URL: Download, https://pypi.org/project/funclibs/#files
Project-URL: Index, https://pypi.org/project/funclibs/
Project-URL: Source, https://github.com/johannes-programming/funclibs/
Project-URL: Website, https://funclibs.johannes-programming.online/
Classifier: Development Status :: 3 - Alpha
Classifier: License :: OSI Approved :: MIT License
Classifier: Natural Language :: English
Classifier: Operating System :: OS Independent
Classifier: Programming Language :: Python
Classifier: Programming Language :: Python :: 3
Classifier: Programming Language :: Python :: 3 :: Only
Classifier: Typing :: Typed
Requires-Python: >=3.11
License-File: LICENSE.txt
Requires-Dist: copyable<2,>=1.0
Requires-Dist: datarepr<2,>=1.1
Requires-Dist: frozendict<3,>=2.4.6
Requires-Dist: setdoc<2,>=1.2.8
Dynamic: license-file
